howtool/__init__.py
howtool/py.typed
howtool/parsers/__init__.py
howtool/parsers/module_doc_parser.py
howtool_version/__init__.py
howtool-0.0.1.dist-info/LICENSE
howtool-0.0.1.dist-info/METADATA
howtool-0.0.1.dist-info/WHEEL
howtool-0.0.1.dist-info/top_level.txt
howtool-0.0.1.dist-info/RECORD
